ann/ANNFaiss.py
ann/ANNMilvus.py
ann/MilvusANN.py
ann/__init__.py
ann/utils.py
ann/utils/__init__.py
ann/utils/data_processor_utils.py
ann/utils/logger.py
easyann/__init__.py
easyann/ann.py
easyann/ann_service.py
easyann/cli.py
easyann/utils.py
easyann-2021.2.1.15.42.6.dist-info/LICENSE
easyann-2021.2.1.15.42.6.dist-info/METADATA
easyann-2021.2.1.15.42.6.dist-info/WHEEL
easyann-2021.2.1.15.42.6.dist-info/entry_points.txt
easyann-2021.2.1.15.42.6.dist-info/top_level.txt
easyann-2021.2.1.15.42.6.dist-info/RECORD
