Metadata-Version: 2.1
Name: easyann
Version: 2021.2.1.15.42.6
Summary: description
Home-page: https://github.com/Jie-Yuan/easyann
Author: JieYuan
Author-email: 313303303@qq.com
Maintainer: JieYuan
Maintainer-email: 313303303@qq.com
License: MIT
Keywords: tool wheel,yuanjie,utils
Platform: all
Classifier: Operating System :: OS Independent
Classifier: Intended Audience :: Developers
Classifier: License :: OSI Approved :: MIT License
Classifier: Programming Language :: Python
Classifier: Programming Language :: Python :: Implementation
Requires-Python: >=3.5
Requires-Dist: pymilvus
